.gitignore
CHANGELOG.rst
LICENSE
MANIFEST.in
README.rst
requirements-test.txt
requirements.txt
runtests.py
setup.cfg
setup.py
admin_top_models/__init__.py
admin_top_models/apps.py
admin_top_models/middleware.py
admin_top_models/models.py
admin_top_models/settings.py
admin_top_models/utils.py
admin_top_models/migrations/__init__.py
django_admin_top_models.egg-info/PKG-INFO
django_admin_top_models.egg-info/SOURCES.txt
django_admin_top_models.egg-info/dependency_links.txt
django_admin_top_models.egg-info/not-zip-safe
django_admin_top_models.egg-info/requires.txt
django_admin_top_models.egg-info/top_level.txt
tests/__init__.py
tests/urls.py
tests/views.py
tests/templates/empty.html