Metadata-Version: 1.1
Name: django-admin-top-models
Version: 1.1.0
Summary: Put most used and important models to the top of your Django admin index.
Home-page: https://github.com/KostyaEsmukov/django-admin-top-models
Author: Kostya Esmukov
Author-email: kostya@esmukov.ru
License: LPGL
Keywords: django modeladmin admin reorder top
Platform: UNKNOWN
Classifier: Development Status :: 5 - Production/Stable
Classifier: Environment :: Web Environment
Classifier: Framework :: Django
Classifier: License :: OSI Approved :: GNU Lesser General Public License v3 (LGPLv3)
Classifier: Natural Language :: English
Classifier: Operating System :: OS Independent
Classifier: Programming Language :: Python :: 2.7
Classifier: Programming Language :: Python :: 3
Classifier: Programming Language :: Python :: 3.3
Classifier: Programming Language :: Python :: 3.4
Classifier: Programming Language :: Python :: 3.5
